pypokergui
tests
