Metadata-Version: 1.1
Name: PyPokerGUI
Version: 0.0.5
Summary: GUI application for PyPokerEngine
Home-page: https://github.com/ishikota/PyPokerGUI
Author: ishikota
Author-email: ishikota086@gmail.com
License: MIT
Keywords: python poker engine gui
Platform: UNKNOWN
Classifier: Development Status :: 5 - Production/Stable
Classifier: License :: OSI Approved :: MIT License
